paibox/__init__.py
paibox/_logging/__init__.py
paibox/_logging/base.py
paibox/_logging/registrations.py
paibox/backend/__init__.py
paibox/backend/checker.py
paibox/backend/conf_exporting.py
paibox/backend/conf_types.py
paibox/backend/constrs.py
paibox/backend/context.py
paibox/backend/graph_utils.py
paibox/backend/graphs.py
paibox/backend/group.py
paibox/backend/kernel_unrolling.py
paibox/backend/mapper.py
paibox/backend/placement.py
paibox/backend/routing.py
paibox/backend/segment_utils.py
paibox/backend/sub_utils.py
paibox/backend/tiling.py
paibox/backend/types.py
paibox/base.py
paibox/collector.py
paibox/components/__init__.py
paibox/components/_modules.py
paibox/components/functional.py
paibox/components/modules.py
paibox/components/neuron/__init__.py
paibox/components/neuron/base.py
paibox/components/neuron/neurons.py
paibox/components/neuron/utils.py
paibox/components/projection.py
paibox/components/synapses/__init__.py
paibox/components/synapses/base.py
paibox/components/synapses/conv_types.py
paibox/components/synapses/conv_utils.py
paibox/components/synapses/learning.py
paibox/components/synapses/lut.py
paibox/components/synapses/synapses.py
paibox/components/synapses/transforms.py
paibox/components/synapses/weight_dtype.py
paibox/context.py
paibox/exceptions.py
paibox/mixin.py
paibox/naming.py
paibox/network.py
paibox/node.py
paibox/simulator/__init__.py
paibox/simulator/encoder.py
paibox/simulator/simulator.py
paibox/simulator/utils.py
paibox/tools.py
paibox/types.py
paibox/utils.py
paibox-1.3.0.dist-info/METADATA
paibox-1.3.0.dist-info/WHEEL
paibox-1.3.0.dist-info/licenses/LICENSE
paibox-1.3.0.dist-info/RECORD
