Metadata-Version: 2.4
Name: paibox
Version: 1.3.0
Summary: Toolchain of PAICORE
License: GPL-3.0-or-later
License-File: LICENSE
Keywords: PAICORE,neuromorphic-chip,toolchain,brain-inspired-ai
Author: Ziru Pan
Author-email: zrpan@stu.pku.edu.cn
Maintainer: Siyuan Gao
Maintainer-email: siyuan-gao@outlook.com
Requires-Python: >=3.10
Classifier: Development Status :: 4 - Beta
Classifier: Intended Audience :: Science/Research
Classifier: License :: OSI Approved :: GNU General Public License v3 or later (GPLv3+)
Classifier: Operating System :: OS Independent
Classifier: Programming Language :: Python :: 3 :: Only
Classifier: Programming Language :: Python :: 3.10
Classifier: Programming Language :: Python :: 3.11
Classifier: Programming Language :: Python :: 3.12
Classifier: Programming Language :: Python :: 3.13
Classifier: Programming Language :: Python :: 3.14
Classifier: Topic :: Scientific/Engineering :: Artificial Intelligence
Classifier: Topic :: Software Development :: Compilers
Requires-Dist: numpy (>=2.1.0,<3.0.0)
Requires-Dist: paicorelib (>=1.5.1,<1.6.0) ; platform_machine != "armv7l"
Requires-Dist: pydantic (>=2.0.3,<3.0.0)
Project-URL: Documentation, https://github.com/PAICookers/PAIBox#readme
Project-URL: Homepage, https://github.com/PAICookers/PAIBox
Project-URL: Repository, https://github.com/PAICookers/PAIBox
